polyglotdb/__init__.py
polyglotdb/_version.py
polyglotdb/config.py
polyglotdb/exceptions.py
polyglotdb/pgdb.py
polyglotdb/structure.py
polyglotdb/utils.py
polyglotdb/acoustics/.DS_Store
polyglotdb/acoustics/__init__.py
polyglotdb/acoustics/classes.py
polyglotdb/acoustics/intensity.py
polyglotdb/acoustics/io.py
polyglotdb/acoustics/other.py
polyglotdb/acoustics/segments.py
polyglotdb/acoustics/utils.py
polyglotdb/acoustics/formants/__init__.py
polyglotdb/acoustics/formants/base.py
polyglotdb/acoustics/formants/formants_bandwidth.praat
polyglotdb/acoustics/formants/helper.py
polyglotdb/acoustics/formants/multiple_num_formants.praat
polyglotdb/acoustics/formants/refined.py
polyglotdb/acoustics/pitch/__init__.py
polyglotdb/acoustics/pitch/base.py
polyglotdb/acoustics/pitch/helper.py
polyglotdb/acoustics/vot/__init__.py
polyglotdb/acoustics/vot/base.py
polyglotdb/client/__init__.py
polyglotdb/client/client.py
polyglotdb/corpus/__init__.py
polyglotdb/corpus/annotated.py
polyglotdb/corpus/audio.py
polyglotdb/corpus/base.py
polyglotdb/corpus/context.py
polyglotdb/corpus/importable.py
polyglotdb/corpus/lexical.py
polyglotdb/corpus/pause.py
polyglotdb/corpus/phonological.py
polyglotdb/corpus/spoken.py
polyglotdb/corpus/structured.py
polyglotdb/corpus/summarized.py
polyglotdb/corpus/syllabic.py
polyglotdb/corpus/utterance.py
polyglotdb/databases/__init__.py
polyglotdb/databases/config.py
polyglotdb/databases/influxdb.conf
polyglotdb/databases/neo4j.conf
polyglotdb/io/__init__.py
polyglotdb/io/discoursedata.py
polyglotdb/io/helper.py
polyglotdb/io/enrichment/__init__.py
polyglotdb/io/enrichment/features.py
polyglotdb/io/enrichment/helper.py
polyglotdb/io/enrichment/lexical.py
polyglotdb/io/enrichment/spoken.py
polyglotdb/io/exporters/__init__.py
polyglotdb/io/exporters/base.py
polyglotdb/io/exporters/csv.py
polyglotdb/io/exporters/textgrid.py
polyglotdb/io/importer/__init__.py
polyglotdb/io/importer/from_csv.py
polyglotdb/io/importer/to_csv.py
polyglotdb/io/inspect/__init__.py
polyglotdb-1.4.0.dist-info/licenses/LICENSE
polyglotdb-1.4.0.dist-info/METADATA
polyglotdb-1.4.0.dist-info/WHEEL
polyglotdb-1.4.0.dist-info/entry_points.txt
polyglotdb-1.4.0.dist-info/top_level.txt
polyglotdb-1.4.0.dist-info/RECORD
