Metadata-Version: 2.4
Name: polyglotdb
Version: 1.4.0
Home-page: https://github.com/MontrealCorpusTools/PolyglotDB
Author: Montreal Corpus Tools
Author-email: michael.e.mcauliffe@gmail.com
License: MIT
Keywords: phonology,corpus,phonetics
Classifier: Development Status :: 3 - Alpha
Classifier: Intended Audience :: Science/Research
Classifier: License :: OSI Approved :: MIT License
Classifier: Operating System :: OS Independent
Classifier: Programming Language :: Python
Classifier: Programming Language :: Python :: 3
Classifier: Topic :: Scientific/Engineering
Classifier: Topic :: Text Processing :: Linguistic
License-File: LICENSE
Requires-Dist: conch-sounds
Requires-Dist: influxdb
Requires-Dist: librosa
Requires-Dist: neo4j
Requires-Dist: praatio
Requires-Dist: requests
Requires-Dist: scipy
Requires-Dist: tqdm
Requires-Dist: pywin32; os_name == "nt"
Provides-Extra: test
Requires-Dist: pytest; extra == "test"
Dynamic: license-file
